wirescale/__init__.py
wirescale/__main__.py
wirescale/version.py
wirescale/wirescale.py
wirescale/communications/__init__.py
wirescale/communications/checkers.py
wirescale/communications/common.py
wirescale/communications/connection_pair.py
wirescale/communications/messages.py
wirescale/communications/systemd.py
wirescale/communications/tcp_client.py
wirescale/communications/tcp_server.py
wirescale/communications/udp_server.py
wirescale/communications/unix_client.py
wirescale/communications/unix_server.py
wirescale/parsers/__init__.py
wirescale/parsers/args.py
wirescale/parsers/parsers.py
wirescale/parsers/utils.py
wirescale/parsers/validators.py
wirescale/scripts/wirescale-autoremove
wirescale/scripts/wirescale-completion
wirescale/systemd/wirescaled.service
wirescale/systemd/wirescaled.socket
wirescale/vpn/__init__.py
wirescale/vpn/exit_node.py
wirescale/vpn/iptables.py
wirescale/vpn/recover.py
wirescale/vpn/tsmanager.py
wirescale/vpn/watch.py
wirescale/vpn/wgconfig.py
wirescale-1.0.3.dist-info/LICENSE
wirescale-1.0.3.dist-info/METADATA
wirescale-1.0.3.dist-info/WHEEL
wirescale-1.0.3.dist-info/entry_points.txt
wirescale-1.0.3.dist-info/top_level.txt
wirescale-1.0.3.dist-info/zip-safe
wirescale-1.0.3.dist-info/RECORD
