Metadata-Version: 2.2
Name: wirescale
Version: 1.0.3
Summary: Wirescale: Secure, Efficient Connectivity. Elevate your network with stable WireGuard tunnels over Tailscale, enhancing speed and flexibility with customizable configuration.
Home-page: https://github.com/fernandoenzo/wirescale/
Download-URL: https://github.com/fernandoenzo/wirescale/releases/
Author: Fernando Enzo Guarini
Author-email: fernandoenzo@gmail.com
Maintainer: 
Maintainer-email: 
License: AGPLv3+
Keywords: wireguard tunnel tunneling vpn tailscale secure networking mesh p2p peer-to-peer ip link route routing net internet ping subnet subnetting
Platform: any
Classifier: Development Status :: 5 - Production/Stable
Classifier: Intended Audience :: End Users/Desktop
Classifier: Intended Audience :: System Administrators
Classifier: Intended Audience :: Telecommunications Industry
Classifier: License :: OSI Approved :: GNU Affero General Public License v3 or later (AGPLv3+)
Classifier: Natural Language :: English
Classifier: Operating System :: POSIX :: Linux
Classifier: Programming Language :: Python :: 3 :: Only
Classifier: Programming Language :: Python :: 3.11
Classifier: Programming Language :: Python :: 3.12
Classifier: Programming Language :: Python :: 3.13
Classifier: Topic :: Communications
Classifier: Topic :: Internet
Classifier: Topic :: System :: Networking
Classifier: Topic :: Utilities
Requires-Python: >=3.11
License-File: LICENSE
Requires-Dist: cryptography==44.0.2
Requires-Dist: netifaces==0.11.0
Requires-Dist: parallel-utils==1.3.1
Requires-Dist: websockets==14.2
Dynamic: author
Dynamic: author-email
Dynamic: classifier
Dynamic: description
Dynamic: description-content-type
Dynamic: download-url
Dynamic: home-page
Dynamic: keywords
Dynamic: license
Dynamic: platform
Dynamic: requires-dist
Dynamic: requires-python
Dynamic: summary
